jsuniv_sllib/__init__.py
jsuniv_sllib/test.py
jsuniv_sllib/classification/__init__.py
jsuniv_sllib/classification/app.py
jsuniv_sllib/classification/config.py
jsuniv_sllib/classification/dataset.py
jsuniv_sllib/classification/evalution.py
jsuniv_sllib/classification/predict.py
jsuniv_sllib/classification/split_dataset.py
jsuniv_sllib/classification/test.py
jsuniv_sllib/classification/train.py
jsuniv_sllib/classification/utils.py
jsuniv_sllib/classification/visual_model.py
jsuniv_sllib/classification/models/AlexNet.py
jsuniv_sllib/classification/models/DenseNet.py
jsuniv_sllib/classification/models/GoogleNet.py
jsuniv_sllib/classification/models/LeNet.py
jsuniv_sllib/classification/models/ResNet.py
jsuniv_sllib/classification/models/SeNet.py
jsuniv_sllib/classification/models/VggNet.py
jsuniv_sllib/classification/models/__init__.py
jsuniv_sllib/detection/__init__.py
jsuniv_sllib/detection/models/__init__.py
jsuniv_sllib/segementation/__init__.py
jsuniv_sllib/segementation/config.py
jsuniv_sllib/segementation/dataset.py
jsuniv_sllib/segementation/evalution.py
jsuniv_sllib/segementation/predict.py
jsuniv_sllib/segementation/split_dataset.py
jsuniv_sllib/segementation/test.py
jsuniv_sllib/segementation/train.py
jsuniv_sllib/segementation/models/BiSeNet.py
jsuniv_sllib/segementation/models/DFANet.py
jsuniv_sllib/segementation/models/DFN.py
jsuniv_sllib/segementation/models/DeconvNet.py
jsuniv_sllib/segementation/models/DeepLab_V3_plus.py
jsuniv_sllib/segementation/models/ENet.py
jsuniv_sllib/segementation/models/ExFuseNet.py
jsuniv_sllib/segementation/models/FCN.py
jsuniv_sllib/segementation/models/FusionNet.py
jsuniv_sllib/segementation/models/GCN.py
jsuniv_sllib/segementation/models/LinkNet.py
jsuniv_sllib/segementation/models/RedNet.py
jsuniv_sllib/segementation/models/SegNet.py
jsuniv_sllib/segementation/models/U_Net.py
jsuniv_sllib/segementation/models/U_Net_plus_plus.py
jsuniv_sllib-0.2.dist-info/METADATA
jsuniv_sllib-0.2.dist-info/RECORD
jsuniv_sllib-0.2.dist-info/WHEEL
jsuniv_sllib-0.2.dist-info/top_level.txt
