Metadata-Version: 2.1
Name: jsuniv-sllib
Version: 0.2
Summary: AIAgorithmPack
Home-page: https://github.com/Major357/major_s
Author: jsuniv_sllib
Author-email: 1171657161@qq.com
License: UNKNOWN
Platform: UNKNOWN
